README.md
setup.py
fogdog/__init__.py
fogdog/_session.py
fogdog/_susan.py
fogdog/cooker.py
fogdog/forecaster.py
fogdog/logger.py
fogdog/multip.py
fogdog/session.py
fogdog/susan.py
fogdog.egg-info/PKG-INFO
fogdog.egg-info/SOURCES.txt
fogdog.egg-info/dependency_links.txt
fogdog.egg-info/requires.txt
fogdog.egg-info/top_level.txt
fogdog.egg-info/zip-safe